darwinio/__init__.py
darwinio/__main__.py
darwinio/brain.py
darwinio/constants.py
darwinio/distribution.py
darwinio/genome.py
darwinio/graphical_sim.py
darwinio/organism.py
darwinio/stats.py
darwinio/assets/art/archaebacteria_halophile.png
darwinio/assets/art/archaebacteria_methanogen.png
darwinio/assets/art/archaebacteria_thermoacidophile.png
darwinio/assets/art/eubacteria_BGA.png
darwinio/assets/art/eubacteria_mycoplasma.png
darwinio/assets/art/eubacteroa_chemosynthetic.png
darwinio/assets/art/fungi-ascomycetes.png
darwinio/assets/art/fungi-basidiomycetes.png
darwinio/assets/art/fungi-deuteromycetes.png
darwinio/assets/art/fungi-phycomycetes.png
darwinio/assets/art/grass.png
darwinio/assets/art/metaphyta-algae.png
darwinio/assets/art/metaphyta-angiospermae.png
darwinio/assets/art/metaphyta-bryophyta.png
darwinio/assets/art/metaphyta-gymnospermae.png
darwinio/assets/art/metaphyta-pterdiophyta.png
darwinio/assets/art/protista_dinoflagellate.png
darwinio/assets/art/protista_euglena.png
darwinio/assets/art/protista_protozoan.png
darwinio/assets/art/protista_slimemould.png
darwinio/assets/art/sand.png
darwinio/assets/art/snow.png
darwinio/assets/art/theme.json
darwinio/assets/art/water.png
darwinio/assets/audio/Darwinio.ogg
darwinio-0.12.0.dist-info/METADATA
darwinio-0.12.0.dist-info/WHEEL
darwinio-0.12.0.dist-info/entry_points.txt
darwinio-0.12.0.dist-info/licenses/LICENSE.md
darwinio-0.12.0.dist-info/RECORD
