Metadata-Version: 2.1
Name: darwinio
Version: 0.12.0
Summary: An evolution simulator
Project-URL: Homepage, https://github.com/tusharhero/darwinio
Project-URL: Bug Tracker, https://github.com/tusharhero/darwinio/issues
Author-email: Tushar Maharana <tusharhero@sdf.org>, Mihir Nallagonda <adhikshithamihir@gmail.com>
License-File: LICENSE.md
Classifier: License :: OSI Approved :: GNU General Public License v3 or later (GPLv3+)
Classifier: Operating System :: OS Independent
Classifier: Programming Language :: Python :: 3 :: Only
Requires-Python: >=3.7
Requires-Dist: matplotlib
Requires-Dist: nilsimsa>=0.3.8
Requires-Dist: numpy
Requires-Dist: pandas
Requires-Dist: pygame-ce>=2.2.1
Requires-Dist: pygame-gui>=0.6.9
Requires-Dist: pyqt5
